ta17/__init__.py
ta17/src/__init__.py
ta17/src/config.py
ta17/src/dataset.py
ta17/src/preprocessing.py
ta17/src/report.py
ta17/src/dags/__init__.py
ta17/src/dags/inference.py
ta17/src/dags/training.py
ta17/src/entities/__init__.py
ta17/src/entities/data_params.py
ta17/src/entities/params.py
ta17/src/entities/paths.py
ta17/src/entities/train_params.py
ta17/src/logs/dag_processor_manager/dag_processor_manager.log
ta17/src/logs/scheduler/2024-12-22/training.py.log
ta17/src/modeling/__init__.py
ta17/src/modeling/base_model.py
ta17/src/modeling/train.py
ta17/src/modeling/train_decision_tree.py
ta17/src/modeling/train_logistic_regression.py
ta17/src/modeling/train_random_forest.py
ta17-0.0.1.dist-info/WHEEL
ta17-0.0.1.dist-info/METADATA
ta17-0.0.1.dist-info/RECORD
