Metadata-Version: 2.3
Name: ta17
Version: 0.0.1
Summary: MLOps course at MISIS 2024
Author: Timur Allayarov
Requires-Python: ~=3.10
Classifier: Programming Language :: Python :: 3
